atmospyre/__init__.py
atmospyre/loggers/__init__.py
atmospyre/loggers/sensor_logger.py
atmospyre/loggers/strategies/__init__.py
atmospyre/loggers/strategies/saver.py
atmospyre/loggers/strategies/writer.py
atmospyre/loggers/strategies/savers/__init__.py
atmospyre/loggers/strategies/savers/json.py
atmospyre/loggers/strategies/writers/__init__.py
atmospyre/loggers/strategies/writers/csv.py
atmospyre/scheduler/__init__.py
atmospyre/scheduler/logger_scheduler.py
atmospyre/scheduler/scheduler_dispatch_tag.py
atmospyre/scheduler/_template/__init__.py
atmospyre/scheduler/_template/backend_template.py
atmospyre/scheduler/schedule/__init__.py
atmospyre/scheduler/schedule/schedule_backend.py
atmospyre/sensors/__init__.py
atmospyre/sensors/sensor.py
atmospyre/sensors/_template/__init__.py
atmospyre/sensors/_template/sensor_template.py
atmospyre/sensors/backends/__init__.py
atmospyre/sensors/backends/minimalmodbus.py
atmospyre/sensors/backends/_template/__init__.py
atmospyre/sensors/backends/_template/backend_template.py
atmospyre/sensors/implementations/__init__.py
atmospyre/sensors/implementations/co2/__init__.py
atmospyre/sensors/implementations/co2/vaisala/__init__.py
atmospyre/sensors/implementations/co2/vaisala/gmp252.py
atmospyre/sensors/implementations/radon/__init__.py
atmospyre/sensors/implementations/radon/radontec/__init__.py
atmospyre/sensors/implementations/radon/radontec/alphatracer.py
atmospyre/sensors/read_tag/__init__.py
atmospyre/sensors/read_tag/metadata.py
atmospyre/sensors/read_tag/read_tag.py
atmospyre/sensors/read_tag/strategies/__init__.py
atmospyre/sensors/read_tag/strategies/extractor.py
atmospyre/sensors/read_tag/strategies/printer.py
atmospyre/sensors/read_tag/strategies/extractors/__init__.py
atmospyre/sensors/read_tag/strategies/extractors/json.py
atmospyre/sensors/read_tag/strategies/printers/__init__.py
atmospyre/sensors/read_tag/strategies/printers/default.py
atmospyre-1.0.0.dist-info/licenses/LICENSE.md
atmospyre-1.0.0.dist-info/METADATA
atmospyre-1.0.0.dist-info/WHEEL
atmospyre-1.0.0.dist-info/top_level.txt
atmospyre-1.0.0.dist-info/RECORD
