Metadata-Version: 2.4
Name: atmospyre
Version: 1.0.0
Summary: Modbus sensor communication library
Author-email: Leon Keim <leon.keim@iws.uni-stuttgart.de>
License-Expression: GPL-3.0-or-later
Project-URL: Documentation, https://pages.iws.uni-stuttgart.de/measurements/atmospyre/
Project-URL: Issues, https://git.iws.uni-stuttgart.de/measurements/atmospyre/-/issues
Project-URL: Repository, https://git.iws.uni-stuttgart.de/measurements/atmospyre
Keywords: modbus,sensors,logging,data-acquisition
Classifier: Development Status :: 5 - Production/Stable
Classifier: Intended Audience :: Science/Research
Classifier: Programming Language :: Python :: 3
Classifier: Programming Language :: Python :: 3.10
Classifier: Programming Language :: Python :: 3.11
Classifier: Programming Language :: Python :: 3.12
Requires-Python: >=3.10
License-File: LICENSE.md
Requires-Dist: multipledispatch>=0.6.0
Provides-Extra: minimalmodbus
Requires-Dist: minimalmodbus>=2.0.0; extra == "minimalmodbus"
Provides-Extra: schedule
Requires-Dist: schedule>=1.2.2; extra == "schedule"
Provides-Extra: recommended
Requires-Dist: minimalmodbus>=2.0.0; extra == "recommended"
Requires-Dist: schedule>=1.2.2; extra == "recommended"
Provides-Extra: all
Requires-Dist: minimalmodbus>=2.0.0; extra == "all"
Requires-Dist: schedule>=1.2.2; extra == "all"
Provides-Extra: dev
Requires-Dist: pytest>=7.0; extra == "dev"
Requires-Dist: pytest-mock>=3.10; extra == "dev"
Requires-Dist: pytest-cov>=4.0; extra == "dev"
Requires-Dist: minimalmodbus>=2.0.0; extra == "dev"
Requires-Dist: schedule>=1.2.2; extra == "dev"
Dynamic: license-file
